neuromeka/__init__.py
neuromeka/ecat.py
neuromeka/eye.py
neuromeka/indy.py
neuromeka/indydcp3.py
neuromeka/moby.py
neuromeka/motor.py
neuromeka/common/__init__.py
neuromeka/common/config.py
neuromeka/common/dcp_addr.py
neuromeka/common/global_timer.py
neuromeka/common/jsmin.py
neuromeka/common/limits.py
neuromeka/common/singleton_meta.py
neuromeka/common/utils.py
neuromeka/common/property/Application.py
neuromeka/common/property/Collision.py
neuromeka/common/property/Log.py
neuromeka/common/property/Modbus.py
neuromeka/common/property/Motion.py
neuromeka/common/property/Timer.py
neuromeka/common/property/TrackConveyor.py
neuromeka/common/property/Vision.py
neuromeka/common/property/__init__.py
neuromeka/proto/__init__.py
neuromeka/proto/common_msgs_pb2.py
neuromeka/proto/common_msgs_pb2_grpc.py
neuromeka/proto/config_msgs_pb2.py
neuromeka/proto/config_msgs_pb2_grpc.py
neuromeka/proto/config_pb2.py
neuromeka/proto/config_pb2_grpc.py
neuromeka/proto/control_msgs_pb2.py
neuromeka/proto/control_msgs_pb2_grpc.py
neuromeka/proto/control_pb2.py
neuromeka/proto/control_pb2_grpc.py
neuromeka/proto/device_msgs_pb2.py
neuromeka/proto/device_msgs_pb2_grpc.py
neuromeka/proto/device_pb2.py
neuromeka/proto/device_pb2_grpc.py
neuromeka/proto/ethercat_msgs_pb2.py
neuromeka/proto/ethercat_msgs_pb2_grpc.py
neuromeka/proto/ethercat_pb2.py
neuromeka/proto/ethercat_pb2_grpc.py
neuromeka/proto/eyetask_pb2.py
neuromeka/proto/eyetask_pb2_grpc.py
neuromeka/proto/grpc_wrapper.py
neuromeka/proto/linear_pb2.py
neuromeka/proto/linear_pb2_grpc.py
neuromeka/proto/moby_msgs_pb2.py
neuromeka/proto/moby_msgs_pb2_grpc.py
neuromeka/proto/moby_pb2.py
neuromeka/proto/moby_pb2_grpc.py
neuromeka/proto/plotting_pb2.py
neuromeka/proto/plotting_pb2_grpc.py
neuromeka/proto/rtde_msgs_pb2.py
neuromeka/proto/rtde_msgs_pb2_grpc.py
neuromeka/proto/rtde_pb2.py
neuromeka/proto/rtde_pb2_grpc.py
neuromeka/proto/shared_msgs_pb2.py
neuromeka/proto/shared_msgs_pb2_grpc.py
neuromeka/proto/teleop_dev_pb2.py
neuromeka_clients3-3.0.5.dist-info/LICENSE
neuromeka_clients3-3.0.5.dist-info/METADATA
neuromeka_clients3-3.0.5.dist-info/WHEEL
neuromeka_clients3-3.0.5.dist-info/top_level.txt
neuromeka_clients3-3.0.5.dist-info/RECORD
