Metadata-Version: 2.1
Name: neuromeka-clients3
Version: 3.0.5
Summary: Neuromeka client protocols for Indy, IndyEye, Moby, Ecat, and Motor
Home-page: https://github.com/neuromeka-robotics/neuromeka-clients3
Author: Neuromeka
Author-email: youngjin.heo@neuromeka.com
Classifier: Development Status :: 3 - Alpha
Classifier: Intended Audience :: Developers
Classifier: License :: OSI Approved :: MIT License
Classifier: Operating System :: OS Independent
Classifier: Programming Language :: Python :: 3
Classifier: Programming Language :: Python :: 3.6
Classifier: Programming Language :: Python :: 3.7
Classifier: Programming Language :: Python :: 3.8
Requires-Python: >=3.6
License-File: LICENSE
Requires-Dist: grpcio ==1.39.0
Requires-Dist: grpcio-tools ==1.39.0
Requires-Dist: protobuf ==3.17.3
Requires-Dist: requests ==2.22.0
Requires-Dist: Pillow ==9.5.0
Requires-Dist: numpy ==1.21.6
Requires-Dist: pyModbusTCP ==0.2.1
Requires-Dist: netifaces ==0.11.0
